lovely/__init__.py
lovely/dog/__init__.py
lovely/dog/message.py
lucklylss_lovely-0.1.dist-info/METADATA
lucklylss_lovely-0.1.dist-info/WHEEL
lucklylss_lovely-0.1.dist-info/top_level.txt
lucklylss_lovely-0.1.dist-info/RECORD
