Metadata-Version: 2.1
Name: lucklylss-lovely
Version: 0.1
Summary: Our abbreviations are lzq, one is Luo Ziqi, the other is Liu Zhiqing!
Author: luo_zi_qi and liu_zhi_qing
License: UNKNOWN
Platform: UNKNOWN
